pystrategy/EW.py
pystrategy/EWStrategy.py
pystrategy/GMR.py
pystrategy/GMRStrategy.py
pystrategy/MaxDrawdown.py
pystrategy/Strategy.py
pystrategy/__init__.py
pystrategy/pystrategy.py
pystrategy-0.0.3.dist-info/METADATA
pystrategy-0.0.3.dist-info/WHEEL
pystrategy-0.0.3.dist-info/top_level.txt
pystrategy-0.0.3.dist-info/RECORD
