Metadata-Version: 2.1
Name: pystrategy
Version: 0.0.3
Summary: UNKNOWN
Home-page: https://github.com/faprieto96/pystrategy
Author: Francisco A. Prieto Rodriguez, Francisco de Asís Fernández Navarro, David Becerra Alonso
License: UNKNOWN
Platform: UNKNOWN
Classifier: Programming Language :: Python :: 3
Classifier: License :: OSI Approved :: MIT License
Classifier: Operating System :: OS Independent
Requires-Python: >=3.0
